FCMHelpers.py
HDBScanHelpers.py
MiscHelpers.py
SOMsHelpers.py
dataPreprocessing.py
fuzzy_clustering.py
minisom.py
acse_9_irp_wafflescore-1.0.5.dist-info/LICENSE
acse_9_irp_wafflescore-1.0.5.dist-info/METADATA
acse_9_irp_wafflescore-1.0.5.dist-info/WHEEL
acse_9_irp_wafflescore-1.0.5.dist-info/top_level.txt
acse_9_irp_wafflescore-1.0.5.dist-info/RECORD
