Metadata-Version: 2.1
Name: acse-9-irp-wafflescore
Version: 1.0.5
Summary: ML for Automatic Facies Classification 
Home-page: https://github.com/msc-acse/acse-9-independent-research-project-wafflescore
Author: Nitchakul Pipitvej
Author-email: np2618@ic.ac.uk
License: UNKNOWN
Platform: UNKNOWN
Classifier: Programming Language :: Python :: 3
Classifier: License :: OSI Approved :: MIT License
Classifier: Operating System :: OS Independent
